tencentcloud/__init__.py
tencentcloud/iotcloud/__init__.py
tencentcloud/iotcloud/v20180614/__init__.py
tencentcloud/iotcloud/v20180614/errorcodes.py
tencentcloud/iotcloud/v20180614/iotcloud_client.py
tencentcloud/iotcloud/v20180614/models.py
tencentcloud/iotcloud/v20210408/__init__.py
tencentcloud/iotcloud/v20210408/errorcodes.py
tencentcloud/iotcloud/v20210408/iotcloud_client.py
tencentcloud/iotcloud/v20210408/models.py
tencentcloud_sdk_python_iotcloud-3.0.1459.dist-info/METADATA
tencentcloud_sdk_python_iotcloud-3.0.1459.dist-info/WHEEL
tencentcloud_sdk_python_iotcloud-3.0.1459.dist-info/top_level.txt
tencentcloud_sdk_python_iotcloud-3.0.1459.dist-info/RECORD
